{
    "affiliation": "UCLA",
    "cites_per_year": {
        "2017": 4,
        "2018": 8,
        "2019": 45,
        "2020": 29
    },
    "citedby": 89,
    "citedby5y": 89,
    "coauthors": [],
    "email": "@g.ucla.edu",
    "hindex": 5,
    "hindex5y": 5,
    "i10index": 3,
    "i10index5y": 3,
    "id": "ia9cfUoAAAAJ",
    "interests": [],
    "name": "JD Knotts",
    "publications": [
        {
            "bib": {
                "title": "Towards an unconscious neural reinforcement intervention for common fears",
                "cites": "44",
                "year": "2018"
            },
            "id_citations": "ia9cfUoAAAAJ:qjMakFHDy7sC",
            "source": "citations"
        },
        {
            "bib": {
                "title": "Transcranial magnetic stimulation to visual cortex induces suboptimal introspection",
                "cites": "13",
                "year": "2017"
            },
            "id_citations": "ia9cfUoAAAAJ:9yKSN-GCB0IC",
            "source": "citations"
        },
        {
            "bib": {
                "title": "Subjective inflation: phenomenology\u2019s get-rich-quick scheme",
                "cites": "11",
                "year": "2019"
            },
            "id_citations": "ia9cfUoAAAAJ:IjCSPb-OGe4C",
            "source": "citations"
        },
        {
            "bib": {
                "title": "Continuous flash suppression and monocular pattern masking impact subjective awareness similarly",
                "cites": "6",
                "year": "2018"
            },
            "id_citations": "ia9cfUoAAAAJ:2osOgNQ5qMEC",
            "source": "citations"
        },
        {
            "bib": {
                "title": "Neuroscience: the key to consciousness may not be under the streetlight",
                "cites": "6",
                "year": "2018"
            },
            "id_citations": "ia9cfUoAAAAJ:UeHWp8X0CEIC",
            "source": "citations"
        },
        {
            "bib": {
                "title": "Clarifying signal detection theoretic interpretations of the M\u00fcller\u2013Lyer and sound-induced flash illusions",
                "cites": "5",
                "year": "2016"
            },
            "id_citations": "ia9cfUoAAAAJ:u5HHmVD_uO8C",
            "source": "citations"
        },
        {
            "bib": {
                "title": "Multivoxel patterns for perceptual confidence are associated with false color detection",
                "cites": "2",
                "year": "2019"
            },
            "id_citations": "ia9cfUoAAAAJ:W7OEmFMy1HYC",
            "source": "citations"
        },
        {
            "bib": {
                "title": "Identifying multivariate patterns for illusory color perception using decoded fMRI neurofeedback",
                "cites": "1",
                "year": "2018"
            },
            "id_citations": "ia9cfUoAAAAJ:zYLM7Y9cAGgC",
            "source": "citations"
        },
        {
            "bib": {
                "title": "Towards an unconscious neurotherapy for common fears",
                "cites": "1",
                "year": "2017"
            },
            "id_citations": "ia9cfUoAAAAJ:u-x6o8ySG0sC",
            "source": "citations"
        },
        {
            "bib": {
                "title": "Defending subjective inflation: An inference to the best explanation",
                "cites": "0",
                "year": "2020"
            },
            "id_citations": "ia9cfUoAAAAJ:eQOLeE2rZwMC",
            "source": "citations"
        },
        {
            "bib": {
                "title": "Stochastic Resonance and Perceptual Decision Making Inattention",
                "cites": "0",
                "year": "2020"
            },
            "id_citations": "ia9cfUoAAAAJ:ufrVoPGSRksC",
            "source": "citations"
        },
        {
            "bib": {
                "title": "New measures of agency from an adaptive sensorimotor task",
                "cites": "0",
                "year": "2020"
            },
            "id_citations": "ia9cfUoAAAAJ:WF5omc3nYNoC",
            "source": "citations"
        },
        {
            "bib": {
                "title": "Subjective confidence judgments for motion direction discrimination are centrally biased despite matched objective performance in the periphery",
                "cites": "0",
                "year": "2019"
            },
            "id_citations": "ia9cfUoAAAAJ:YsMSGLbcyi4C",
            "source": "citations"
        },
        {
            "bib": {
                "title": "On objective and subjective visual perception",
                "cites": "0",
                "year": "2019"
            },
            "id_citations": "ia9cfUoAAAAJ:Y0pCki6q_DkC",
            "source": "citations"
        },
        {
            "bib": {
                "title": "Correction to: Continuous flash suppression and monocular pattern masking impact subjective awareness similarly.",
                "cites": "0",
                "year": "2018"
            },
            "id_citations": "ia9cfUoAAAAJ:Tyk-4Ss8FVUC",
            "source": "citations"
        }
    ],
    "url_picture": "https://scholar.google.com/citations?view_op=medium_photo&user=ia9cfUoAAAAJ"
}
