{
    "affiliation": "Professor of Neuroscience & Psychology, Princeton University",
    "cites_per_year": {
        "2003": 21,
        "2004": 29,
        "2005": 59,
        "2006": 62,
        "2007": 144,
        "2008": 142,
        "2009": 186,
        "2010": 208,
        "2011": 302,
        "2012": 265,
        "2013": 418,
        "2014": 335,
        "2015": 403,
        "2016": 504,
        "2017": 569,
        "2018": 769,
        "2019": 869,
        "2020": 722
    },
    "citedby": 6069,
    "citedby5y": 3846,
    "coauthors": [
        {
            "affiliation": "Silver Professor of Neural Science, Mathematics, and Psychology, NYU",
            "id": "MplR7_cAAAAJ",
            "name": "Eero P Simoncelli"
        },
        {
            "affiliation": "Columbia University",
            "id": "FayXlTYAAAAJ",
            "name": "Liam Paninski"
        },
        {
            "affiliation": "Professor of Neurosurgery and Ophthalmology, Stanford University",
            "id": "PMM9J2AAAAAJ",
            "name": "E.J. Chichilnisky"
        },
        {
            "affiliation": "Google Research",
            "id": "x5bC-UwAAAAJ",
            "name": "Jon Shlens"
        },
        {
            "affiliation": "Associate Professor of Neurobiology and Behavior, Stony Brook University",
            "id": "CsmltusAAAAJ",
            "name": "Il Memming Park"
        },
        {
            "affiliation": "Professor of Neuroscience & Psychology, The University of Texas at Austin",
            "id": "0HqT53cAAAAJ",
            "name": "Alex Huk (Alexander C Huk, AC Huk)"
        },
        {
            "affiliation": "University of Maryland",
            "id": "UJm-TkYAAAAJ",
            "name": "Jacob L Yates"
        },
        {
            "affiliation": "University of Oregon, Departments of Biology and Mathematics",
            "id": "ZDaThWgAAAAJ",
            "name": "Yashar Ahmadian"
        },
        {
            "affiliation": "Postdoc, University of Chicago",
            "id": "934mZKEAAAAJ",
            "name": "Kenneth W Latimer"
        },
        {
            "affiliation": "Sony AI",
            "id": "-8szmOAAAAAJ",
            "name": "Evan Archer"
        },
        {
            "affiliation": "Johns Hopkins University, Department of Biomedical Engineering",
            "id": "c8RKLp0AAAAJ",
            "name": "Adam Charles"
        },
        {
            "affiliation": "Professor of Psychology and Neuroscience, Princeton University",
            "id": "A4ycnDQAAAAJ",
            "name": "Kenneth A. Norman"
        },
        {
            "affiliation": "Professor of Psychology and Neuroscience",
            "id": "VRw8v4kAAAAJ",
            "name": "Uri Hasson"
        },
        {
            "affiliation": "PhD of Neuroscience in Princeton University",
            "id": "ptGYJiEAAAAJ",
            "name": "Anqi Wu"
        },
        {
            "affiliation": "National Institutes of Health",
            "id": "9WhWqakAAAAJ",
            "name": "Leor Katz"
        },
        {
            "affiliation": "University of Washington",
            "id": "cQ78NGQAAAAJ",
            "name": "Miriam Meister"
        },
        {
            "affiliation": "Professor of Psychology and Neuroscience, Princeton University",
            "id": "5NUNoKwAAAAJ",
            "name": "Yael Niv"
        },
        {
            "affiliation": "Associate Professor, Neuroscience & Psychology, Princeton University",
            "id": "Z-R6fz0AAAAJ",
            "name": "Ilana B. Witten"
        },
        {
            "affiliation": "Princeton University",
            "id": "_LHH8DgAAAAJ",
            "name": "David W. Tank"
        },
        {
            "affiliation": "mv333@columbia.edu",
            "id": "SZXjSg8AAAAJ",
            "name": "Michael Vidne"
        }
    ],
    "email": "@princeton.edu",
    "hindex": 35,
    "hindex5y": 29,
    "i10index": 65,
    "i10index5y": 61,
    "id": "-ElvJ9wAAAAJ",
    "interests": [
        "computational neuroscience",
        "neural coding",
        "machine learning",
        "decision-making",
        "vision"
    ],
    "name": "Jonathan Pillow",
    "publications": [
        {
            "bib": {
                "title": "Spatio-temporal correlations and visual signalling in a complete neuronal population",
                "cites": "1167",
                "year": "2008"
            },
            "id_citations": "-ElvJ9wAAAAJ:u5HHmVD_uO8C",
            "source": "citations"
        },
        {
            "bib": {
                "title": "Spike-triggered neural characterization",
                "cites": "417",
                "year": "2006"
            },
            "id_citations": "-ElvJ9wAAAAJ:2osOgNQ5qMEC",
            "source": "citations"
        },
        {
            "bib": {
                "title": "Prediction and decoding of retinal ganglion cell responses with a probabilistic spiking model",
                "cites": "364",
                "year": "2005"
            },
            "id_citations": "-ElvJ9wAAAAJ:9yKSN-GCB0IC",
            "source": "citations"
        },
        {
            "bib": {
                "title": "Characterization of neural responses with stochastic stimuli",
                "cites": "330",
                "year": "2004"
            },
            "id_citations": "-ElvJ9wAAAAJ:d1gkVwhDpl0C",
            "source": "citations"
        },
        {
            "bib": {
                "title": "Maximum likelihood estimation of a stochastic integrate-and-fire neural encoding model",
                "cites": "301",
                "year": "2004"
            },
            "id_citations": "-ElvJ9wAAAAJ:u-x6o8ySG0sC",
            "source": "citations"
        },
        {
            "bib": {
                "title": "Statistical models for neural encoding, decoding, and optimal stimulus design",
                "cites": "258",
                "year": "2007"
            },
            "id_citations": "-ElvJ9wAAAAJ:qjMakFHDy7sC",
            "source": "citations"
        },
        {
            "bib": {
                "title": "Discovering event structure in continuous narrative perception and memory",
                "cites": "231",
                "year": "2017"
            },
            "id_citations": "-ElvJ9wAAAAJ:XtJa11BXPS4C",
            "source": "citations"
        },
        {
            "bib": {
                "title": "Single-trial spike trains in parietal cortex reveal discrete steps during decision-making",
                "cites": "217",
                "year": "2015"
            },
            "id_citations": "-ElvJ9wAAAAJ:I9gX6wnfuA8C",
            "source": "citations"
        },
        {
            "bib": {
                "title": "Dissociated functional significance of decision-related activity in the primate dorsal stream",
                "cites": "180",
                "year": "2016"
            },
            "id_citations": "-ElvJ9wAAAAJ:8p8iYwVyaVcC",
            "source": "citations"
        },
        {
            "bib": {
                "title": "Dimensionality reduction in neural models: an information-theoretic generalization of spike-triggered average and covariance analysis",
                "cites": "155",
                "year": "2006"
            },
            "id_citations": "-ElvJ9wAAAAJ:zYLM7Y9cAGgC",
            "source": "citations"
        },
        {
            "bib": {
                "title": "Encoding and decoding in parietal cortex during sensorimotor decision-making",
                "cites": "150",
                "year": "2014"
            },
            "id_citations": "-ElvJ9wAAAAJ:GiYFt9mpioMC",
            "source": "citations"
        },
        {
            "bib": {
                "title": "Model-based decoding, information estimation, and change-point detection techniques for multineuron spike trains",
                "cites": "149",
                "year": "2011"
            },
            "id_citations": "-ElvJ9wAAAAJ:Y0pCki6q_DkC",
            "source": "citations"
        },
        {
            "bib": {
                "title": "Computational approaches to fMRI analysis",
                "cites": "114",
                "year": "2017"
            },
            "id_citations": "-ElvJ9wAAAAJ:1xBWf43XMUgC",
            "source": "citations"
        },
        {
            "bib": {
                "title": "Modeling the impact of common noise inputs on the network activity of retinal ganglion cells",
                "cites": "111",
                "year": "2012"
            },
            "id_citations": "-ElvJ9wAAAAJ:Wp0gIr-vW9MC",
            "source": "citations"
        },
        {
            "bib": {
                "title": "Perceptual completion across the vertical meridian and the role of early visual cortex",
                "cites": "103",
                "year": "2002"
            },
            "id_citations": "-ElvJ9wAAAAJ:UeHWp8X0CEIC",
            "source": "citations"
        },
        {
            "bib": {
                "title": "A Model-Based Spike Sorting Algorithm for Removing Correlation Artifacts in Multi-Neuron Recordings",
                "cites": "101",
                "year": "2013"
            },
            "id_citations": "-ElvJ9wAAAAJ:R3hNpaxXUhUC",
            "source": "citations"
        },
        {
            "bib": {
                "title": "Efficient Markov chain Monte Carlo methods for decoding neural spike trains",
                "cites": "91",
                "year": "2011"
            },
            "id_citations": "-ElvJ9wAAAAJ:WF5omc3nYNoC",
            "source": "citations"
        },
        {
            "bib": {
                "title": "Combined social and spatial coding in a descending projection from the prefrontal cortex",
                "cites": "88",
                "year": "2017"
            },
            "id_citations": "-ElvJ9wAAAAJ:cF7EPgIk0B4C",
            "source": "citations"
        },
        {
            "bib": {
                "title": "Biases in white noise analysis due to non-Poisson spike generation",
                "cites": "86",
                "year": "2003"
            },
            "id_citations": "-ElvJ9wAAAAJ:IjCSPb-OGe4C",
            "source": "citations"
        },
        {
            "bib": {
                "title": "Volumetric two-photon imaging of neurons using stereoscopy (vTwINS)",
                "cites": "71",
                "year": "2016"
            },
            "id_citations": "-ElvJ9wAAAAJ:ybfzIt2tCtgC",
            "source": "citations"
        },
        {
            "bib": {
                "title": "Receptive Field Inference with Localized Priors",
                "cites": "69",
                "year": "2011"
            },
            "id_citations": "-ElvJ9wAAAAJ:aqlVkmm33-oC",
            "source": "citations"
        },
        {
            "bib": {
                "title": "Bayesian Spike-Triggered Covariance Analysis",
                "cites": "67",
                "year": "2011"
            },
            "id_citations": "-ElvJ9wAAAAJ:M3ejUd6NZC8C",
            "source": "citations"
        },
        {
            "bib": {
                "title": "Functional dissection of signal and noise in MT and LIP during decision-making",
                "cites": "60",
                "year": "2017"
            },
            "id_citations": "-ElvJ9wAAAAJ:uoRD4RTSUPoC",
            "source": "citations"
        },
        {
            "bib": {
                "title": "Fully Bayesian inference for neural models with negative-binomial spiking",
                "cites": "56",
                "year": "2012"
            },
            "id_citations": "-ElvJ9wAAAAJ:qUcmZB5y_30C",
            "source": "citations"
        },
        {
            "bib": {
                "title": "Likelihood-based approaches to modeling the neural code",
                "cites": "54",
                "year": "2007"
            },
            "id_citations": "-ElvJ9wAAAAJ:YsMSGLbcyi4C",
            "source": "citations"
        },
        {
            "bib": {
                "title": "Spectral methods for neural characterization using generalized quadratic models",
                "cites": "52",
                "year": "2013"
            },
            "id_citations": "-ElvJ9wAAAAJ:N6_Y7JlWxwsC",
            "source": "citations"
        },
        {
            "bib": {
                "title": "Bayesian entropy estimation for countable discrete distributions",
                "cites": "51",
                "year": "2014"
            },
            "id_citations": "-ElvJ9wAAAAJ:mB3voiENLucC",
            "source": "citations"
        },
        {
            "bib": {
                "title": "Comparing integrate-and-fire models estimated using intracellular and extracellular data",
                "cites": "50",
                "year": "2005"
            },
            "id_citations": "-ElvJ9wAAAAJ:Tyk-4Ss8FVUC",
            "source": "citations"
        },
        {
            "bib": {
                "title": "Characterizing neural dependencies with copula models",
                "cites": "49",
                "year": "2009"
            },
            "id_citations": "-ElvJ9wAAAAJ:UebtZRa9Y70C",
            "source": "citations"
        },
        {
            "bib": {
                "title": "Capturing the dynamical repertoire of single neurons with generalized linear models",
                "cites": "44",
                "year": "2017"
            },
            "id_citations": "-ElvJ9wAAAAJ:It0W0vAlS5QC",
            "source": "citations"
        },
        {
            "bib": {
                "title": "Gaussian process based nonlinear latent structure discovery in multivariate spike train data",
                "cites": "41",
                "year": "2017"
            },
            "id_citations": "-ElvJ9wAAAAJ:4E1Y8I9HL1wC",
            "source": "citations"
        },
        {
            "bib": {
                "title": "Bayesian latent structure discovery from multi-neuron recordings",
                "cites": "39",
                "year": "2016"
            },
            "id_citations": "-ElvJ9wAAAAJ:hEXC_dOfxuUC",
            "source": "citations"
        },
        {
            "bib": {
                "title": "Low-dimensional models of neural population activity in sensory cortical circuits",
                "cites": "39",
                "year": "2014"
            },
            "id_citations": "-ElvJ9wAAAAJ:mVC4hKzE2FoC",
            "source": "citations"
        },
        {
            "bib": {
                "title": "The equivalence of information-theoretic and likelihood-based methods for neural dimensionality reduction",
                "cites": "38",
                "year": "2015"
            },
            "id_citations": "-ElvJ9wAAAAJ:CCeGMaHljPEC",
            "source": "citations"
        },
        {
            "bib": {
                "title": "Maximum Likelihood Estimation of a Stochastic Integrate-and-Fire Neural Model.",
                "cites": "37",
                "year": "2003"
            },
            "id_citations": "-ElvJ9wAAAAJ:e3CVSTJ63dQC",
            "source": "citations"
        },
        {
            "bib": {
                "title": "Neural characterization in partially observed populations of spiking neurons",
                "cites": "34",
                "year": "2008"
            },
            "id_citations": "-ElvJ9wAAAAJ:LkGwnXOMwfcC",
            "source": "citations"
        },
        {
            "bib": {
                "title": "Heterogeneous response dynamics in retinal ganglion cells: the interplay of predictive coding and adaptation",
                "cites": "28",
                "year": "2010"
            },
            "id_citations": "-ElvJ9wAAAAJ:KlAtU1dfN6UC",
            "source": "citations"
        },
        {
            "bib": {
                "title": "Continuous psychophysics: Target-tracking to measure visual sensitivity",
                "cites": "25",
                "year": "2015"
            },
            "id_citations": "-ElvJ9wAAAAJ:B2rIPIGFPLEC",
            "source": "citations"
        },
        {
            "bib": {
                "title": "Time-rescaling methods for the estimation and assessment of non-Poisson neural encoding models",
                "cites": "25",
                "year": "2009"
            },
            "id_citations": "-ElvJ9wAAAAJ:hqOjcs7Dif8C",
            "source": "citations"
        },
        {
            "bib": {
                "title": "Inferring sparse representations of continuous signals with continuous orthogonal matching pursuit",
                "cites": "24",
                "year": "2014"
            },
            "id_citations": "-ElvJ9wAAAAJ:Nnq8S6OXqDYC",
            "source": "citations"
        },
        {
            "bib": {
                "title": "Bayesian active learning with localized priors for fast receptive field characterization",
                "cites": "21",
                "year": "2012"
            },
            "id_citations": "-ElvJ9wAAAAJ:QIV2ME_5wuYC",
            "source": "citations"
        },
        {
            "bib": {
                "title": "Dethroning the Fano Factor: a flexible, model-based approach to partitioning neural variability",
                "cites": "20",
                "year": "2018"
            },
            "id_citations": "-ElvJ9wAAAAJ:MNNNGtAgD4EC",
            "source": "citations"
        },
        {
            "bib": {
                "title": "A Bayesian method for reducing bias in neural representational similarity analysis",
                "cites": "19",
                "year": "2016"
            },
            "id_citations": "-ElvJ9wAAAAJ:vD2iS2Kej30C",
            "source": "citations"
        },
        {
            "bib": {
                "title": "Bayesian and quasi-Bayesian estimators for mutual information from discrete data",
                "cites": "19",
                "year": "2013"
            },
            "id_citations": "-ElvJ9wAAAAJ:_Qo2XoVZTnwC",
            "source": "citations"
        },
        {
            "bib": {
                "title": "Bayesian entropy estimation for binary spike train data using parametric prior knowledge",
                "cites": "19",
                "year": "2013"
            },
            "id_citations": "-ElvJ9wAAAAJ:5LPo_wSKItgC",
            "source": "citations"
        },
        {
            "bib": {
                "title": "Active learning of neural response functions with Gaussian processes",
                "cites": "19",
                "year": "2011"
            },
            "id_citations": "-ElvJ9wAAAAJ:ULOm3_A8WrAC",
            "source": "citations"
        },
        {
            "bib": {
                "title": "Representational structure or task structure? Bias in neural representational similarity analysis and a Bayesian method for reducing bias",
                "cites": "18",
                "year": "2019"
            },
            "id_citations": "-ElvJ9wAAAAJ:Q3-QASNKTMEC",
            "source": "citations"
        },
        {
            "bib": {
                "title": "Bayesian active learning of neural firing rate maps with transformed gaussian process priors",
                "cites": "18",
                "year": "2014"
            },
            "id_citations": "-ElvJ9wAAAAJ:vxA22ZmNLkoC",
            "source": "citations"
        },
        {
            "bib": {
                "title": "An international laboratory for systems and computational neuroscience",
                "cites": "17",
                "year": "2017"
            },
            "id_citations": "-ElvJ9wAAAAJ:U5uP8zs9lfgC",
            "source": "citations"
        },
        {
            "bib": {
                "title": "Adaptive Bayesian methods for closed-loop neurophysiology",
                "cites": "17",
                "year": "2016"
            },
            "id_citations": "-ElvJ9wAAAAJ:yZoBfgUKqwcC",
            "source": "citations"
        },
        {
            "bib": {
                "title": "Bayesian estimation of discrete entropy with mixtures of stick-breaking priors",
                "cites": "17",
                "year": "2012"
            },
            "id_citations": "-ElvJ9wAAAAJ:hC7cP41nSMkC",
            "source": "citations"
        },
        {
            "bib": {
                "title": "Exploiting gradients and Hessians in Bayesian optimization and Bayesian quadrature",
                "cites": "16",
                "year": "2017"
            },
            "id_citations": "-ElvJ9wAAAAJ:cdwqcPQS8ssC",
            "source": "citations"
        },
        {
            "bib": {
                "title": "Sparse Bayesian structure learning with dependent relevance determination priors",
                "cites": "16",
                "year": "2014"
            },
            "id_citations": "-ElvJ9wAAAAJ:GJVTs2krol4C",
            "source": "citations"
        },
        {
            "bib": {
                "title": "Error-correcting dynamics in visual working memory",
                "cites": "15",
                "year": "2019"
            },
            "id_citations": "-ElvJ9wAAAAJ:1paMEeroeoQC",
            "source": "citations"
        },
        {
            "bib": {
                "title": "Discrete stepping and nonlinear ramping dynamics underlie spiking responses of LIP neurons during decision-making",
                "cites": "15",
                "year": "2019"
            },
            "id_citations": "-ElvJ9wAAAAJ:I-2NeQpV75MC",
            "source": "citations"
        },
        {
            "bib": {
                "title": "Adaptive optimal training of animal behavior",
                "cites": "15",
                "year": "2016"
            },
            "id_citations": "-ElvJ9wAAAAJ:NXYAu82O0W8C",
            "source": "citations"
        },
        {
            "bib": {
                "title": "Inferring synaptic conductances from spike trains with a biophysically inspired point process model",
                "cites": "15",
                "year": "2014"
            },
            "id_citations": "-ElvJ9wAAAAJ:WMtz-WDmgKQC",
            "source": "citations"
        },
        {
            "bib": {
                "title": "Bayesian inference for low rank spatiotemporal neural receptive fields",
                "cites": "15",
                "year": "2013"
            },
            "id_citations": "-ElvJ9wAAAAJ:k_IJM867U9cC",
            "source": "citations"
        },
        {
            "bib": {
                "title": "Unsupervised identification of the internal states that shape natural behavior",
                "cites": "13",
                "year": "2019"
            },
            "id_citations": "-ElvJ9wAAAAJ:9VeumLvkZSQC",
            "source": "citations"
        },
        {
            "bib": {
                "title": "Encoding multiple orientations in a recurrent network",
                "cites": "12",
                "year": "2000"
            },
            "id_citations": "-ElvJ9wAAAAJ:ufrVoPGSRksC",
            "source": "citations"
        },
        {
            "bib": {
                "title": "Convolutional Spike-triggered Covariance Analysis for Neural Subunit Models",
                "cites": "11",
                "year": "2015"
            },
            "id_citations": "-ElvJ9wAAAAJ:IHkkN1K1AlAC",
            "source": "citations"
        },
        {
            "bib": {
                "title": "Learning a latent manifold of odor representations from neural responses in piriform cortex",
                "cites": "10",
                "year": "2018"
            },
            "id_citations": "-ElvJ9wAAAAJ:hB2aVRuWZNwC",
            "source": "citations"
        },
        {
            "bib": {
                "title": "Efficient inference for time-varying behavior during learning",
                "cites": "10",
                "year": "2018"
            },
            "id_citations": "-ElvJ9wAAAAJ:jKT558fuBk8C",
            "source": "citations"
        },
        {
            "bib": {
                "title": "Bayesian efficient coding",
                "cites": "10",
                "year": "2017"
            },
            "id_citations": "-ElvJ9wAAAAJ:2Q0AJrNhS-QC",
            "source": "citations"
        },
        {
            "bib": {
                "title": "Universal models for binary spike patterns using centered Dirichlet processes",
                "cites": "10",
                "year": "2013"
            },
            "id_citations": "-ElvJ9wAAAAJ:_mQi-xiA4oYC",
            "source": "citations"
        },
        {
            "bib": {
                "title": "Inferring synaptic inputs from spikes with a conductance-based neural encoding model",
                "cites": "9",
                "year": "2019"
            },
            "id_citations": "-ElvJ9wAAAAJ:5VjbC5aozO0C",
            "source": "citations"
        },
        {
            "bib": {
                "title": "Adaptive stimulus selection for multi-alternative psychometric functions with lapses",
                "cites": "9",
                "year": "2018"
            },
            "id_citations": "-ElvJ9wAAAAJ:BCdnXsLIVDwC",
            "source": "citations"
        },
        {
            "bib": {
                "title": "Systematic misperceptions of 3-D motion explained by Bayesian inference",
                "cites": "7",
                "year": "2018"
            },
            "id_citations": "-ElvJ9wAAAAJ:Cvh0bltMcLgC",
            "source": "citations"
        },
        {
            "bib": {
                "title": "Scaling the Poisson GLM to massive neural datasets through polynomial approximations",
                "cites": "7",
                "year": "2018"
            },
            "id_citations": "-ElvJ9wAAAAJ:uEM9VtRl8xsC",
            "source": "citations"
        },
        {
            "bib": {
                "title": "Majority of choice-related variability in perceptual decisions is present in early sensory cortex",
                "cites": "7",
                "year": "2017"
            },
            "id_citations": "-ElvJ9wAAAAJ:L7vk9XBBNxgC",
            "source": "citations"
        },
        {
            "bib": {
                "title": "Bayesian Structure Learning for Functional Neuroimaging",
                "cites": "7",
                "year": "2013"
            },
            "id_citations": "-ElvJ9wAAAAJ:TQgYirikUcIC",
            "source": "citations"
        },
        {
            "bib": {
                "title": "Is population activity more than the sum of its parts?",
                "cites": "6",
                "year": "2017"
            },
            "id_citations": "-ElvJ9wAAAAJ:_IsBomjs8bsC",
            "source": "citations"
        },
        {
            "bib": {
                "title": "A decoder-based spike train metric for analyzing the neural code in the retina",
                "cites": "6",
                "year": "2009"
            },
            "id_citations": "-ElvJ9wAAAAJ:roLk4NBRz8UC",
            "source": "citations"
        },
        {
            "bib": {
                "title": "Dependent relevance determination for smooth and structured sparse regression",
                "cites": "5",
                "year": "2019"
            },
            "id_citations": "-ElvJ9wAAAAJ:g30IDTdgJMgC",
            "source": "citations"
        },
        {
            "bib": {
                "title": "Shared representational geometry across neural networks",
                "cites": "5",
                "year": "2018"
            },
            "id_citations": "-ElvJ9wAAAAJ:BFa5h04uPMwC",
            "source": "citations"
        },
        {
            "bib": {
                "title": "Lawful tracking of visual motion in humans, macaques, and marmosets in a naturalistic, continuous, and untrained behavioral context",
                "cites": "5",
                "year": "2018"
            },
            "id_citations": "-ElvJ9wAAAAJ:jRIwE-1ttnoC",
            "source": "citations"
        },
        {
            "bib": {
                "title": "Running reduces firing but improves coding in rodent higher-order visual cortex",
                "cites": "5",
                "year": "2017"
            },
            "id_citations": "-ElvJ9wAAAAJ:feST4K8J0scC",
            "source": "citations"
        },
        {
            "bib": {
                "title": "Model-based targeted dimensionality reduction for neuronal population data",
                "cites": "4",
                "year": "2018"
            },
            "id_citations": "-ElvJ9wAAAAJ:U3qCfcK-7lkC",
            "source": "citations"
        },
        {
            "bib": {
                "title": "A comparison of deep learning and linear-nonlinear cascade approaches to neural encoding",
                "cites": "4",
                "year": "2018"
            },
            "id_citations": "-ElvJ9wAAAAJ:cww_0JKUTDwC",
            "source": "citations"
        },
        {
            "bib": {
                "title": "No cause for pause: new analyses of ramping and stepping dynamics in LIP (Rebuttal to Response to Reply to Comment on Latimer et al 2015)",
                "cites": "3",
                "year": "2017"
            },
            "id_citations": "-ElvJ9wAAAAJ:J4E9jCG1tHUC",
            "source": "citations"
        },
        {
            "bib": {
                "title": "Optimal prior-dependent neural population codes under shared input noise",
                "cites": "3",
                "year": "2014"
            },
            "id_citations": "-ElvJ9wAAAAJ:MGPUR4WVBMEC",
            "source": "citations"
        },
        {
            "bib": {
                "title": "A simple linear readout of MT supports motion direction-discrimination performance",
                "cites": "2",
                "year": "2020"
            },
            "id_citations": "-ElvJ9wAAAAJ:9tXw7Op4-u0C",
            "source": "citations"
        },
        {
            "bib": {
                "title": "Sparse-Coding Variational Auto-Encoders",
                "cites": "2",
                "year": "2018"
            },
            "id_citations": "-ElvJ9wAAAAJ:KIRwYnRZzWQC",
            "source": "citations"
        },
        {
            "bib": {
                "title": "Scalable Bayesian inference for high-dimensional neural receptive fields",
                "cites": "2",
                "year": "2017"
            },
            "id_citations": "-ElvJ9wAAAAJ:GHsHDPAyICYC",
            "source": "citations"
        },
        {
            "bib": {
                "title": "Explaining the especially pink elephant",
                "cites": "2",
                "year": "2015"
            },
            "id_citations": "-ElvJ9wAAAAJ:j8pvxH-kN2QC",
            "source": "citations"
        },
        {
            "bib": {
                "title": "Bayesian inference for latent stepping and ramping models of spike train data",
                "cites": "2",
                "year": "2015"
            },
            "id_citations": "-ElvJ9wAAAAJ:HqhvjgTjE9cC",
            "source": "citations"
        },
        {
            "bib": {
                "title": "Spike train entropy-rate estimation using hierarchical Dirichlet process priors",
                "cites": "2",
                "year": "2013"
            },
            "id_citations": "-ElvJ9wAAAAJ:maZDTaKrznsC",
            "source": "citations"
        },
        {
            "bib": {
                "title": "Correlations and coding with multi-neuronal spike trains in primate retina",
                "cites": "2",
                "year": "2007"
            },
            "id_citations": "-ElvJ9wAAAAJ:QtA78RmWg5MC",
            "source": "citations"
        },
        {
            "bib": {
                "title": "Neural coding and the statistical modeling of neuronal responses",
                "cites": "2",
                "year": "2005"
            },
            "id_citations": "-ElvJ9wAAAAJ:0EnyYjriUFMC",
            "source": "citations"
        },
        {
            "bib": {
                "title": "Extracting the Dynamics of Behavior in Decision-Making Experiments",
                "cites": "1",
                "year": "2020"
            },
            "id_citations": "-ElvJ9wAAAAJ:koF6b02d8EEC",
            "source": "citations"
        },
        {
            "bib": {
                "title": "Poisson balanced spiking networks",
                "cites": "1",
                "year": "2019"
            },
            "id_citations": "-ElvJ9wAAAAJ:oFn-K-OQSCAC",
            "source": "citations"
        },
        {
            "bib": {
                "title": "Prefrontal cortex exhibits multi-dimensional dynamic encoding during decision-making",
                "cites": "1",
                "year": "2019"
            },
            "id_citations": "-ElvJ9wAAAAJ:KsTgnNRry18C",
            "source": "citations"
        },
        {
            "bib": {
                "title": "Detecting and correcting false transients in calcium imaging",
                "cites": "1",
                "year": "2018"
            },
            "id_citations": "-ElvJ9wAAAAJ:ynsZFq2pu0MC",
            "source": "citations"
        },
        {
            "bib": {
                "title": "Stochastic filtering of two-photon imaging using reweighted \u21131",
                "cites": "1",
                "year": "2017"
            },
            "id_citations": "-ElvJ9wAAAAJ:GtqhT-R7ZnwC",
            "source": "citations"
        },
        {
            "bib": {
                "title": "7 Bayesian inference for latent stepping and ramping models of spike train data",
                "cites": "1",
                "year": "2015"
            },
            "id_citations": "-ElvJ9wAAAAJ:6Zm5LS9gQ5UC",
            "source": "citations"
        },
        {
            "bib": {
                "title": "Psychophysical reverse correlation of motion perception",
                "cites": "1",
                "year": "2012"
            },
            "id_citations": "-ElvJ9wAAAAJ:9ZlFYXVOiuMC",
            "source": "citations"
        },
        {
            "bib": {
                "title": "A Probabilistic Network Model of Population Responses",
                "cites": "1",
                "year": "2002"
            },
            "id_citations": "-ElvJ9wAAAAJ:MXK_kJrjxJIC",
            "source": "citations"
        },
        {
            "bib": {
                "title": "High-contrast \"gaudy\" images improve the training of deep neural network models of visual cortex",
                "cites": "0",
                "year": "2020"
            },
            "id_citations": "-ElvJ9wAAAAJ:5bfplxN71z4C",
            "source": "citations"
        },
        {
            "bib": {
                "title": "Unifying and generalizing models of neural dynamics during decision-making",
                "cites": "0",
                "year": "2020"
            },
            "id_citations": "-ElvJ9wAAAAJ:3_f9JqYsqVQC",
            "source": "citations"
        },
        {
            "bib": {
                "title": "Corrections to: Systematic misperceptions",
                "cites": "0",
                "year": "2020"
            },
            "id_citations": "-ElvJ9wAAAAJ:ovGv7akYl-cC",
            "source": "citations"
        },
        {
            "bib": {
                "title": "Identifying signal and noise structure in neural population activity with Gaussian process factor models",
                "cites": "0",
                "year": "2020"
            },
            "id_citations": "-ElvJ9wAAAAJ:SPgmg5JLkoEC",
            "source": "citations"
        },
        {
            "bib": {
                "title": "Fast shared response model for fMRI data",
                "cites": "0",
                "year": "2019"
            },
            "id_citations": "-ElvJ9wAAAAJ:lRPiJ3GhvscC",
            "source": "citations"
        },
        {
            "bib": {
                "title": "Demonstration and quantification of memory-guided saccades in the common marmoset (with comparison to the macaque)",
                "cites": "0",
                "year": "2019"
            },
            "id_citations": "-ElvJ9wAAAAJ:3x-KLxxGyuUC",
            "source": "citations"
        },
        {
            "bib": {
                "title": "Efficient non-conjugate Gaussian process factor models for spike count data using polynomial approximations",
                "cites": "0",
                "year": "2019"
            },
            "id_citations": "-ElvJ9wAAAAJ:h1pkognVyKwC",
            "source": "citations"
        },
        {
            "bib": {
                "title": "Editorial overview: Machine learning, big data, and neuroscience",
                "cites": "0",
                "year": "2019"
            },
            "id_citations": "-ElvJ9wAAAAJ:5F1dSjz1ScoC",
            "source": "citations"
        },
        {
            "bib": {
                "title": "Neural Anatomy and Optical Microscopy (NAOMi) Simulation for evaluating calcium imaging methods",
                "cites": "0",
                "year": "2019"
            },
            "id_citations": "-ElvJ9wAAAAJ:kvJssbFybhEC",
            "source": "citations"
        },
        {
            "bib": {
                "title": "Power-law efficient neural codes provide general link between perceptual bias and discriminability",
                "cites": "0",
                "year": "2018"
            },
            "id_citations": "-ElvJ9wAAAAJ:uPCvBZYD9qUC",
            "source": "citations"
        },
        {
            "bib": {
                "title": "The 8th annual computational and systems neuroscience (Cosyne) meeting",
                "cites": "0",
                "year": "2011"
            },
            "id_citations": "-ElvJ9wAAAAJ:Zph67rFs4hoC",
            "source": "citations"
        },
        {
            "bib": {
                "title": "A general recurrent state space framework for modeling neural dynamics during decision-making",
                "cites": "0"
            },
            "id_citations": "-ElvJ9wAAAAJ:qCaWouos7ogC",
            "source": "citations"
        },
        {
            "bib": {
                "title": "Additive Continuous-time Joint Partitioning of Neural Variability",
                "cites": "0"
            },
            "id_citations": "-ElvJ9wAAAAJ:37Fl7vPTsUIC",
            "source": "citations"
        }
    ],
    "url_picture": "https://scholar.google.com/citations?view_op=medium_photo&user=-ElvJ9wAAAAJ"
}
