{
    "affiliation": "Associate Professor of Neuroscience, Rutgers University",
    "cites_per_year": {
        "2008": 45,
        "2009": 58,
        "2010": 60,
        "2011": 102,
        "2012": 169,
        "2013": 313,
        "2014": 498,
        "2015": 675,
        "2016": 917,
        "2017": 1226,
        "2018": 1300,
        "2019": 1428,
        "2020": 1238
    },
    "citedby": 8135,
    "citedby5y": 6791,
    "coauthors": [
        {
            "affiliation": "Yale University",
            "id": "QVS1AfkAAAAJ",
            "name": "Alan Anticevic"
        },
        {
            "affiliation": "Professor of Psychology, Washington University, Saint Louis",
            "id": "1JNwC9IAAAAJ",
            "name": "Todd S. Braver"
        },
        {
            "affiliation": "Associate Professor of Psychology, University of Ljubljana",
            "id": "faBMKJsAAAAJ",
            "name": "Grega Repov\u0161"
        },
        {
            "affiliation": "Assistant Professor of Psychiatry, Neuroscience, and Physics, Yale University",
            "id": "LCAIVIUAAAAJ",
            "name": "John D. Murray"
        },
        {
            "affiliation": "University of Pittsburgh",
            "id": "3K-mQGsAAAAJ",
            "name": "Walter Schneider"
        },
        {
            "affiliation": "PhD student, Rutgers University",
            "id": "Ym08_RMAAAAJ",
            "name": "Takuya Ito"
        },
        {
            "affiliation": "Research Associate, Rutgers University",
            "id": "T7nPaJUAAAAJ",
            "name": "Ravi D Mill"
        },
        {
            "affiliation": "J. Peter Skirkanich Professor, University of Pennsylvania & Santa Fe Institute",
            "id": "siYpAPsAAAAJ",
            "name": "Danielle S. Bassett"
        },
        {
            "affiliation": "Research Assistant Professor, University of Nebraska-Lincoln",
            "id": "qW2ehCcAAAAJ",
            "name": "Doug Schultz"
        },
        {
            "affiliation": "Global Professor of Neural Science, New York University",
            "id": "cv-YgL0AAAAJ",
            "name": "Xiao-Jing Wang"
        },
        {
            "affiliation": "M.D.-Ph.D., Yale University; Research Track Psychiatry Resident at Mount Sinai School of Medicine",
            "id": "Ry6RUyoAAAAJ",
            "name": "Genevieve Yang"
        },
        {
            "affiliation": "Weill Cornell Medicine",
            "id": "mlNP7HgAAAAJ",
            "name": "Jonathan Power"
        },
        {
            "affiliation": "Yale University",
            "id": "GTvOETIAAAAJ",
            "name": "Philip Corlett"
        },
        {
            "affiliation": "Professor of Psychology, Ben-Gurion University of the Negev",
            "id": "L0KwR5IAAAAJ",
            "name": "Nachshon Meiran"
        },
        {
            "affiliation": "MD/PhD Student, Icahn School of Medicine at Mount Sinai",
            "id": "39x6HmsAAAAJ",
            "name": "Kaustubh R Kulkarni"
        },
        {
            "affiliation": "Researcher, Univertsity Of Pittsburgh",
            "id": "5QsjGf0AAAAJ",
            "name": "Sudhir K Pathak"
        },
        {
            "affiliation": "National Institutes of Health",
            "id": "zvMnvWIAAAAJ",
            "name": "Anderson M. Winkler"
        },
        {
            "affiliation": "Professor of Neuroscience and Psychology, University of California,Berkeley",
            "id": "s7gOlh8AAAAJ",
            "name": "Mark D'Esposito"
        },
        {
            "affiliation": "Washington University",
            "id": "rS5gzhcAAAAJ",
            "name": "Steve Petersen"
        },
        {
            "affiliation": "PhD Candidate, Rutgers University Center for Molecular and Behavioral Neuroscience",
            "id": "YzDTV3UAAAAJ",
            "name": "Carrisa Cocuzza"
        }
    ],
    "email": "@rutgers.edu",
    "hindex": 38,
    "hindex5y": 37,
    "i10index": 48,
    "i10index5y": 46,
    "id": "8FK99kkAAAAJ",
    "interests": [
        "neuroscience",
        "psychology",
        "cognitive control",
        "brain connectivity",
        "brain imaging"
    ],
    "name": "Michael W. Cole",
    "publications": [
        {
            "bib": {
                "title": "Multi-task connectivity reveals flexible hubs for adaptive task control",
                "cites": "934",
                "year": "2013"
            },
            "id_citations": "8FK99kkAAAAJ:M3NEmzRMIkIC",
            "source": "citations"
        },
        {
            "bib": {
                "title": "Intrinsic and task-evoked network architectures of the human brain",
                "cites": "883",
                "year": "2014"
            },
            "id_citations": "8FK99kkAAAAJ:NKlx0PmyA3cC",
            "source": "citations"
        },
        {
            "bib": {
                "title": "The cognitive control network: integrated cortical regions with dissociable functions",
                "cites": "798",
                "year": "2007"
            },
            "id_citations": "8FK99kkAAAAJ:hqOjcs7Dif8C",
            "source": "citations"
        },
        {
            "bib": {
                "title": "The role of default network deactivation in cognition and disease",
                "cites": "634",
                "year": "2012"
            },
            "id_citations": "8FK99kkAAAAJ:hFOr9nPyWt4C",
            "source": "citations"
        },
        {
            "bib": {
                "title": "Global connectivity of prefrontal cortex predicts cognitive control and intelligence",
                "cites": "500",
                "year": "2012"
            },
            "id_citations": "8FK99kkAAAAJ:L8Ckcad2t8MC",
            "source": "citations"
        },
        {
            "bib": {
                "title": "Identifying the brain's most globally connected regions",
                "cites": "420",
                "year": "2010"
            },
            "id_citations": "8FK99kkAAAAJ:8k81kl-MbHgC",
            "source": "citations"
        },
        {
            "bib": {
                "title": "Characterizing thalamo-cortical disturbances in schizophrenia and bipolar illness",
                "cites": "295",
                "year": "2014"
            },
            "id_citations": "8FK99kkAAAAJ:maZDTaKrznsC",
            "source": "citations"
        },
        {
            "bib": {
                "title": "The fronto-parietal control system: A central role in mental health",
                "cites": "272",
                "year": "2014"
            },
            "id_citations": "8FK99kkAAAAJ:J-ba04ztB30C",
            "source": "citations"
        },
        {
            "bib": {
                "title": "Altered global brain signal in schizophrenia",
                "cites": "245",
                "year": "2014"
            },
            "id_citations": "8FK99kkAAAAJ:eJD0kABLposC",
            "source": "citations"
        },
        {
            "bib": {
                "title": "Variable global dysconnectivity and individual differences in schizophrenia",
                "cites": "197",
                "year": "2011"
            },
            "id_citations": "8FK99kkAAAAJ:KlAtU1dfN6UC",
            "source": "citations"
        },
        {
            "bib": {
                "title": "Global Prefrontal and Fronto-Amygdala Dysconnectivity in Bipolar I Disorder with Psychosis History",
                "cites": "189",
                "year": "2012"
            },
            "id_citations": "8FK99kkAAAAJ:ZeXyd9-uunAC",
            "source": "citations"
        },
        {
            "bib": {
                "title": "Activity flow over resting-state networks shapes cognitive task activations",
                "cites": "182",
                "year": "2016"
            },
            "id_citations": "8FK99kkAAAAJ:ZpgFv6i7Z4gC",
            "source": "citations"
        },
        {
            "bib": {
                "title": "Global resting-state functional magnetic resonance imaging analysis identifies frontal cortex, striatal, and cerebellar dysconnectivity in obsessive-compulsive disorder",
                "cites": "168",
                "year": "2014"
            },
            "id_citations": "8FK99kkAAAAJ:hMod-77fHWUC",
            "source": "citations"
        },
        {
            "bib": {
                "title": "Rapid instructed task learning: A new window into the human brain\u2019s unique capacity for flexible cognitive control",
                "cites": "150",
                "year": "2013"
            },
            "id_citations": "8FK99kkAAAAJ:hC7cP41nSMkC",
            "source": "citations"
        },
        {
            "bib": {
                "title": "Canceling planned action: an fMRI study of countermanding saccades",
                "cites": "142",
                "year": "2005"
            },
            "id_citations": "8FK99kkAAAAJ:0EnyYjriUFMC",
            "source": "citations"
        },
        {
            "bib": {
                "title": "Vive les differences! Individual variation in neural mechanisms of executive control",
                "cites": "130",
                "year": "2010"
            },
            "id_citations": "8FK99kkAAAAJ:Zph67rFs4hoC",
            "source": "citations"
        },
        {
            "bib": {
                "title": "Prefrontal dynamics underlying rapid instructed task learning reverse with practice",
                "cites": "124",
                "year": "2010"
            },
            "id_citations": "8FK99kkAAAAJ:kNdYIx-mwKoC",
            "source": "citations"
        },
        {
            "bib": {
                "title": "Heterogeneity within the frontoparietal control network and its relationship to the default and dorsal attention networks",
                "cites": "119",
                "year": "2018"
            },
            "id_citations": "8FK99kkAAAAJ:OlbiQ0ttILcC",
            "source": "citations"
        },
        {
            "bib": {
                "title": "Higher Intelligence Is Associated with Less Task-Related Brain Network Reconfiguration",
                "cites": "119",
                "year": "2016"
            },
            "id_citations": "8FK99kkAAAAJ:Weau3kkTRIMC",
            "source": "citations"
        },
        {
            "bib": {
                "title": "Cingulate cortex: diverging data from humans and monkeys",
                "cites": "118",
                "year": "2009"
            },
            "id_citations": "8FK99kkAAAAJ:3fE2CSJIrl8C",
            "source": "citations"
        },
        {
            "bib": {
                "title": "N-Methyl-D-Aspartate Receptor Antagonist Effects on Prefrontal Cortical Connectivity Better Model Early Than Chronic Schizophrenia",
                "cites": "116",
                "year": "2014"
            },
            "id_citations": "8FK99kkAAAAJ:gL9scSG3K_gC",
            "source": "citations"
        },
        {
            "bib": {
                "title": "Early-course unmedicated schizophrenia patients exhibit elevated prefrontal connectivity associated with longitudinal change",
                "cites": "102",
                "year": "2015"
            },
            "id_citations": "8FK99kkAAAAJ:mS4qin7VKjkC",
            "source": "citations"
        },
        {
            "bib": {
                "title": "A Functional Cartography of Cognitive Systems.",
                "cites": "101",
                "year": "2015"
            },
            "id_citations": "8FK99kkAAAAJ:bxPAEoiBajcC",
            "source": "citations"
        },
        {
            "bib": {
                "title": "Rapid transfer of abstract rules to novel contexts in human lateral prefrontal cortex",
                "cites": "80",
                "year": "2011"
            },
            "id_citations": "8FK99kkAAAAJ:dhFuZR0502QC",
            "source": "citations"
        },
        {
            "bib": {
                "title": "Reward motivation enhances task coding in frontoparietal cortex",
                "cites": "79",
                "year": "2016"
            },
            "id_citations": "8FK99kkAAAAJ:djft3U1LymYC",
            "source": "citations"
        },
        {
            "bib": {
                "title": "Connectivity, pharmacology, and computation: toward a mechanistic understanding of neural system dysfunction in schizophrenia",
                "cites": "76",
                "year": "2013"
            },
            "id_citations": "8FK99kkAAAAJ:blknAaTinKkC",
            "source": "citations"
        },
        {
            "bib": {
                "title": "The power of instructions: Proactive configuration of stimulus\u2013response translation.",
                "cites": "72",
                "year": "2015"
            },
            "id_citations": "8FK99kkAAAAJ:vkz5F8TaVKkC",
            "source": "citations"
        },
        {
            "bib": {
                "title": "When planning results in loss of control: intention-based reflexivity and working-memory",
                "cites": "68",
                "year": "2012"
            },
            "id_citations": "8FK99kkAAAAJ:7PzlFSSx8tAC",
            "source": "citations"
        },
        {
            "bib": {
                "title": "Mapping the human brain's cortical-subcortical functional network organization",
                "cites": "63",
                "year": "2019"
            },
            "id_citations": "8FK99kkAAAAJ:Sf6vrWCRp3YC",
            "source": "citations"
        },
        {
            "bib": {
                "title": "Cognitive task information is transferred between brain regions via resting-state network topology",
                "cites": "63",
                "year": "2017"
            },
            "id_citations": "8FK99kkAAAAJ:qkm5LKljiV4C",
            "source": "citations"
        },
        {
            "bib": {
                "title": "Mediodorsal and Visual Thalamic Connectivity Differ in Schizophrenia and Bipolar Disorder With and Without Psychosis History",
                "cites": "60",
                "year": "2014"
            },
            "id_citations": "8FK99kkAAAAJ:0paDrhnEFY0C",
            "source": "citations"
        },
        {
            "bib": {
                "title": "Amygdala connectivity differs among chronic, early course, and individuals at risk for developing schizophrenia",
                "cites": "57",
                "year": "2014"
            },
            "id_citations": "8FK99kkAAAAJ:t9Ks5LMjN0QC",
            "source": "citations"
        },
        {
            "bib": {
                "title": "From connectome to cognition: the search for mechanism in human functional brain networks",
                "cites": "56",
                "year": "2017"
            },
            "id_citations": "8FK99kkAAAAJ:h-xndbdg2koC",
            "source": "citations"
        },
        {
            "bib": {
                "title": "Lateral Prefrontal Cortex Contributes to Fluid Intelligence Through Multinetwork Connectivity",
                "cites": "48",
                "year": "2015"
            },
            "id_citations": "8FK99kkAAAAJ:-w1eE4La9_EC",
            "source": "citations"
        },
        {
            "bib": {
                "title": "Selection and maintenance of stimulus-response rules during preparation and performance of a spatial choice-reaction task",
                "cites": "47",
                "year": "2007"
            },
            "id_citations": "8FK99kkAAAAJ:5nxA0vEk-isC",
            "source": "citations"
        },
        {
            "bib": {
                "title": "Neural mechanisms for response selection: comparing selection of responses and items from working memory",
                "cites": "45",
                "year": "2007"
            },
            "id_citations": "8FK99kkAAAAJ:MXK_kJrjxJIC",
            "source": "citations"
        },
        {
            "bib": {
                "title": "The behavioral relevance of task information in human prefrontal cortex",
                "cites": "43",
                "year": "2016"
            },
            "id_citations": "8FK99kkAAAAJ:G7txJ4jiatkC",
            "source": "citations"
        },
        {
            "bib": {
                "title": "Task activations produce spurious but systematic inflation of task functional connectivity estimates",
                "cites": "41",
                "year": "2019"
            },
            "id_citations": "8FK99kkAAAAJ:G887dSk7Sz8C",
            "source": "citations"
        },
        {
            "bib": {
                "title": "Advancing functional connectivity research from association to causation",
                "cites": "37",
                "year": "2019"
            },
            "id_citations": "8FK99kkAAAAJ:yL7DKRohVA8C",
            "source": "citations"
        },
        {
            "bib": {
                "title": "The task novelty paradox: Flexible control of inflexible neural pathways during rapid instructed task learning",
                "cites": "33",
                "year": "2017"
            },
            "id_citations": "8FK99kkAAAAJ:S0CDQJw8Yr4C",
            "source": "citations"
        },
        {
            "bib": {
                "title": "Functional connectivity change as shared signal dynamics",
                "cites": "33",
                "year": "2016"
            },
            "id_citations": "8FK99kkAAAAJ:tL5YfqkXb3gC",
            "source": "citations"
        },
        {
            "bib": {
                "title": "Reflexive activation of newly instructed stimulus\u2013response rules: evidence from lateralized readiness potentials in no-go trials",
                "cites": "26",
                "year": "2015"
            },
            "id_citations": "8FK99kkAAAAJ:SEKBqlyTJecC",
            "source": "citations"
        },
        {
            "bib": {
                "title": "Empirical validation of directed functional connectivity",
                "cites": "23",
                "year": "2017"
            },
            "id_citations": "8FK99kkAAAAJ:AkvegQHRDQ8C",
            "source": "citations"
        },
        {
            "bib": {
                "title": "Global connectivity of the fronto-parietal cognitive control network is related to depression symptoms in the general population",
                "cites": "19",
                "year": "2018"
            },
            "id_citations": "8FK99kkAAAAJ:JaLtl8ASYokC",
            "source": "citations"
        },
        {
            "bib": {
                "title": "Conflict detection and resolution rely on a combination of common and distinct cognitive control networks",
                "cites": "19",
                "year": "2017"
            },
            "id_citations": "8FK99kkAAAAJ:rp474-M6Y4oC",
            "source": "citations"
        },
        {
            "bib": {
                "title": "Conflict over Cingulate Cortex: Between-Species Differences in Cingulate May Support Enhanced Cognitive Flexibility in Humans",
                "cites": "19",
                "year": "2010"
            },
            "id_citations": "8FK99kkAAAAJ:ULOm3_A8WrAC",
            "source": "citations"
        },
        {
            "bib": {
                "title": "The human brain traverses a common activation-pattern state space across task and rest",
                "cites": "11",
                "year": "2018"
            },
            "id_citations": "8FK99kkAAAAJ:Wqn_fehR_TUC",
            "source": "citations"
        },
        {
            "bib": {
                "title": "Discovering the Computational Relevance of Brain Network Organization",
                "cites": "10",
                "year": "2020"
            },
            "id_citations": "8FK99kkAAAAJ:pYRxIbzCxX0C",
            "source": "citations"
        },
        {
            "bib": {
                "title": "A role for proactive control in rapid instructed task learning",
                "cites": "7",
                "year": "2018"
            },
            "id_citations": "8FK99kkAAAAJ:QI7uKX5mnFEC",
            "source": "citations"
        },
        {
            "bib": {
                "title": "Looking outside the searchlight",
                "cites": "7",
                "year": "2012"
            },
            "id_citations": "8FK99kkAAAAJ:mB3voiENLucC",
            "source": "citations"
        },
        {
            "bib": {
                "title": "How to study the neural mechanisms of multiple tasks",
                "cites": "6",
                "year": "2019"
            },
            "id_citations": "8FK99kkAAAAJ:kiex5tMzGo8C",
            "source": "citations"
        },
        {
            "bib": {
                "title": "A whole-brain and cross-diagnostic perspective on functional brain network dysfunction",
                "cites": "6",
                "year": "2018"
            },
            "id_citations": "8FK99kkAAAAJ:ef2wPL15CskC",
            "source": "citations"
        },
        {
            "bib": {
                "title": "Integrated Brain Network Architecture Supports Cognitive Task Performance",
                "cites": "6",
                "year": "2016"
            },
            "id_citations": "8FK99kkAAAAJ:-c_eYhz9dBkC",
            "source": "citations"
        },
        {
            "bib": {
                "title": "Similarity Learning with Higher-Order Proximity for Brain Network Analysis",
                "cites": "5",
                "year": "2018"
            },
            "id_citations": "8FK99kkAAAAJ:mo9XK3BEATIC",
            "source": "citations"
        },
        {
            "bib": {
                "title": "The biological basis of rapid instructed task learning",
                "cites": "5",
                "year": "2009"
            },
            "id_citations": "8FK99kkAAAAJ:_kc_bZDykSQC",
            "source": "citations"
        },
        {
            "bib": {
                "title": "Combining multiple functional connectivity methods to improve causal inferences",
                "cites": "4",
                "year": "2020"
            },
            "id_citations": "8FK99kkAAAAJ:uoeYKOKFegwC",
            "source": "citations"
        },
        {
            "bib": {
                "title": "Deep Graph Similarity Learning for Brain Data Analysis",
                "cites": "4",
                "year": "2019"
            },
            "id_citations": "8FK99kkAAAAJ:Q_E8KsG3g9MC",
            "source": "citations"
        },
        {
            "bib": {
                "title": "Transcranial alternating current stimulation attenuates BOLD adaptation and increases functional connectivity",
                "cites": "3",
                "year": "2020"
            },
            "id_citations": "8FK99kkAAAAJ:lOG7zRu2uA8C",
            "source": "citations"
        },
        {
            "bib": {
                "title": "Task-evoked activity quenches neural correlations and variability across cortical areas",
                "cites": "3",
                "year": "2020"
            },
            "id_citations": "8FK99kkAAAAJ:it4f3qIuXWYC",
            "source": "citations"
        },
        {
            "bib": {
                "title": "The situation or the person? Individual and task\u2010evoked differences in BOLD activity",
                "cites": "3",
                "year": "2019"
            },
            "id_citations": "8FK99kkAAAAJ:VHM5RxzNINsC",
            "source": "citations"
        },
        {
            "bib": {
                "title": "Predicting dysfunctional age-related task activations from resting-state network alterations",
                "cites": "2",
                "year": "2020"
            },
            "id_citations": "8FK99kkAAAAJ:nbnL2fqDbzcC",
            "source": "citations"
        },
        {
            "bib": {
                "title": "Estimation and Validation of Individualized Dynamic Brain Models with Resting State fMRI",
                "cites": "2",
                "year": "2020"
            },
            "id_citations": "8FK99kkAAAAJ:2SFquFhkCoYC",
            "source": "citations"
        },
        {
            "bib": {
                "title": "Similarity Learning with Higher-Order Graph Convolutions for Brain Network Analysis",
                "cites": "2",
                "year": "2018"
            },
            "id_citations": "8FK99kkAAAAJ:XR3BWSlh_xcC",
            "source": "citations"
        },
        {
            "bib": {
                "title": "A cortical hierarchy of localized and distributed processes revealed via dissociation of task activations, connectivity changes, and intrinsic timescales",
                "cites": "1",
                "year": "2020"
            },
            "id_citations": "8FK99kkAAAAJ:URGbnSt0D2cC",
            "source": "citations"
        },
        {
            "bib": {
                "title": "Control and Connectivity",
                "cites": "1",
                "year": "2017"
            },
            "id_citations": "8FK99kkAAAAJ:1YatL4jblGcC",
            "source": "citations"
        },
        {
            "bib": {
                "title": "When Planning Results in Loss of Control: Intention-Based Reflexivity and Proactive Control \u2018",
                "cites": "1",
                "year": "2013"
            },
            "id_citations": "8FK99kkAAAAJ:bEWYMUwI8FkC",
            "source": "citations"
        },
        {
            "bib": {
                "title": "Reverse Engineering the Brain with a Circuit Diagram Based on a Segmented Connectome and System Dynamics.",
                "cites": "1",
                "year": "2008"
            },
            "id_citations": "8FK99kkAAAAJ:YOwf2qJgpHMC",
            "source": "citations"
        },
        {
            "bib": {
                "title": "The functional relevance of task-state functional connectivity",
                "cites": "0",
                "year": "2020"
            },
            "id_citations": "8FK99kkAAAAJ:TewouNez5YAC",
            "source": "citations"
        },
        {
            "bib": {
                "title": "Flexible coordinator and switcher hubs for adaptive task control",
                "cites": "0",
                "year": "2020"
            },
            "id_citations": "8FK99kkAAAAJ:dJ_BR67V0s4C",
            "source": "citations"
        },
        {
            "bib": {
                "title": "High Definition Fiber Tracking Exposes Circuit Diagram for Brain Showing Triarchic Representation, Domain General Control, and Metacognitive Subsystems.",
                "cites": "0",
                "year": "2009"
            },
            "id_citations": "8FK99kkAAAAJ:qxL8FJ1GzNcC",
            "source": "citations"
        },
        {
            "bib": {
                "title": "Correction for \u201cHeterogeneity within the frontoparietal control network and its relationship to the default and dorsal attention net-works,\u201d by Matthew L. Dixon, Alejandro De \u2026",
                "cites": "0"
            },
            "id_citations": "8FK99kkAAAAJ:pbQCAAeKvsAC",
            "source": "citations"
        }
    ],
    "url_picture": "https://scholar.google.com/citations?view_op=medium_photo&user=8FK99kkAAAAJ"
}
